MANIFEST.in
README.rst
setup.cfg
setup.py
atg/__init__.py
atg/activities.py
atg/cli.py
atg/commands.py
atg/location.py
atg/utils.py
atg.egg-info/PKG-INFO
atg.egg-info/SOURCES.txt
atg.egg-info/dependency_links.txt
atg.egg-info/entry_points.txt
atg.egg-info/requires.txt
atg.egg-info/top_level.txt