Metadata-Version: 1.1
Name: atg
Version: 0.0.4
Summary: A small timezone utility
Home-page: https://github.com/crodjer/around-the-globe
Author: Rohan Jain
Author-email: crodjer@gmail.com
License: GPLv3+
Keywords: timezones productivity
Platform: UNKNOWN
Classifier: Development Status :: 3 - Alpha
Classifier: Environment :: Console
Classifier: Intended Audience :: Developers
Classifier: Topic :: Utilities
Classifier: Topic :: Office/Business :: Scheduling
Classifier: License :: OSI Approved :: GNU General Public License v3 or later (GPLv3+)
Classifier: Programming Language :: Python :: 2
Classifier: Programming Language :: Python :: 3
